Kkit/__init__.py
Kkit/ksort/__init__.py
Kkit/mder/__init__.py
Kkit/prj_control/__init__.py
Kkit/str2object/__init__.py
Kkit-1.0.2.dist-info/LICENSE
Kkit-1.0.2.dist-info/METADATA
Kkit-1.0.2.dist-info/WHEEL
Kkit-1.0.2.dist-info/top_level.txt
Kkit-1.0.2.dist-info/RECORD
