Metadata-Version: 2.1
Name: Kkit
Version: 1.0.2
Summary: some personnal kits
Home-page: https://github.com/walkureHHH/Kylis_Kit
Author: Kylis
Author-email: 1779599839@qq.com
Project-URL: Bug Tracker, https://github.com/walkureHHH/Kylis_Kit/issues
Classifier: Programming Language :: Python :: 3
Classifier: License :: OSI Approved :: MIT License
Classifier: Operating System :: OS Independent
Requires-Python: >=3.6
License-File: LICENSE
